README.txt
setup.cfg
setup.py
doc/Makefile
doc/contents.rst
doc/make.bat
doc/source/README.txt
doc/source/ToyPB.rst
doc/source/ToyPCB.rst
doc/source/addmodel.rst
doc/source/conf.py
doc/source/index.rst
doc/source/quickstart.rst
doc/source/references.rst
doc/source/summary.rst
doc/source/_static/container.css
doc/source/_static/default.css
doc/source/_static/network.png
share/data/EGFR-ErbB_PCB2009/EGFR-ErbB_PCB2009.csv
share/data/EGFR-ErbB_PCB2009/EGFR-ErbB_PCB2009.dot
share/data/EGFR-ErbB_PCB2009/EGFR-ErbB_PCB2009.sif
share/data/EGFR-ErbB_PCB2009/EGFR-ErbB_PCB2009.svg
share/data/EGFR-ErbB_PCB2009/EGFR-ErbB_PCB2009_ORonly.sif
share/data/EGFR-ErbB_PCB2009/app_para.m
share/data/EGFR-ErbB_PCB2009/description.txt
share/data/EGFR-ErbB_PCB2009/docu.pdf
share/data/EGFR-ErbB_PCB2009/egfgesamt.png
share/data/EGFR-ErbB_PCB2009/egfgesamt_layout.dat
share/data/EGFR-ErbB_PCB2009/metabolites
share/data/EGFR-ErbB_PCB2009/model.dot
share/data/EGFR-ErbB_PCB2009/reactions
share/data/EGFR-ErbB_PCB2009/reactions_notes
share/data/EGFR-ErbB_PCB2009/uniprot.dat
share/data/EGFR-ErbB_PCB2009/data/BoolData-Exp1.csv
share/data/EGFR-ErbB_PCB2009/data/BoolData-Exp2.csv
share/data/EGFR-ErbB_PCB2009/data/RawData-Exp1.csv
share/data/EGFR-ErbB_PCB2009/data/RawData-Exp2.csv
share/data/EGFR-ErbB_PCB2009/data/__init__.py
share/data/ExtLiverBMC2012/MCP_HepG2mod4.csv
share/data/ExtLiverBMC2012/MCP_PriHumod5.csv
share/data/ExtLiverBMC2012/MD-ExtLiverPCB.csv
share/data/ExtLiverBMC2012/PKN-ExtLiverBMC2012.dot
share/data/ExtLiverBMC2012/PKN-ExtLiverBMC2012.sif
share/data/ExtLiverBMC2012/PKN-ExtLiverBMC2012.svg
share/data/ExtLiverBMC2012/PKN-ExtLiverMSBmodUP.sif
share/data/ExtLiverBMC2012/description.txt
share/data/ExtLiverBMC2012/pkn.sif
share/data/ExtLiverPCB/MD-ExtLiverPCB.csv
share/data/ExtLiverPCB/PKN-ExtLiverPCB.dot
share/data/ExtLiverPCB/PKN-ExtLiverPCB.sif
share/data/ExtLiverPCB/PKN-ExtLiverPCB.svg
share/data/ExtLiverPCB/aliases.py
share/data/ExtLiverPCB/description.txt
src/cellnopt.data.egg-info/PKG-INFO
src/cellnopt.data.egg-info/SOURCES.txt
src/cellnopt.data.egg-info/dependency_links.txt
src/cellnopt.data.egg-info/namespace_packages.txt
src/cellnopt.data.egg-info/requires.txt
src/cellnopt.data.egg-info/top_level.txt
