Metadata-Version: 1.1
Name: cellnopt.data
Version: 1.0.1
Summary: data and model repository for http://www.cellnopt.org project
Home-page: ['http://www.ebi.ac.uk/~cokelaer/cellnopt/data']
Author: Thomas Cokelaer
Author-email: cokelaer@ebi.ac.uk
License: GPL
Download-URL: ['http://pypi.python.org/pypi/cellnopt.data']
Keywords: Graph Theory,Genetic Algorithm,Cell Theory,Signalling Pathways,CellNOpt
Platform: Linux
Platform: Unix
Platform: MacOsX
Platform: Windows
Classifier: Development Status :: 3 - Alpha
Classifier: Intended Audience :: Science/Research
Classifier: Intended Audience :: Science/Research
Classifier: License :: OSI Approved :: GNU Library or Lesser General Public License (LGPL)
Classifier: Operating System :: OS Independent
Classifier: Programming Language :: Python :: 2.7
Classifier: Topic :: Software Development :: Libraries :: Python Modules
Classifier: Topic :: Scientific/Engineering :: Bio-Informatics
Classifier: Topic :: Scientific/Engineering :: Information Analysis
Classifier: Topic :: Scientific/Engineering :: Mathematics
Classifier: Topic :: Scientific/Engineering :: Physics
